LICENSE
MANIFEST.in
README.md
pyproject.toml
setup.py
tests/test_alpha_pi_setter.py
tests/test_beambeam2d.py
tests/test_beambeam3d_part1.py
tests/test_beambeam3d_part2.py
tests/test_beambeam_pic.py
tests/test_beambeamstrongstrong2d.py
tests/test_beambeamstrongstrong2d_pi.py
tests/test_beambeamstrongstrong3d.py
tests/test_beambeamstrongstrong3d_pi.py
tests/test_beamstrahlung.py
tests/test_beamstrahlung_pic.py
tests/test_bhabha.py
tests/test_cerrf.py
tests/test_compressed_profile_interp_result.py
tests/test_constant_charge_slicing.py
tests/test_electroncloud.py
tests/test_electronlens_interpolated.py
tests/test_element_with_slicer_filling_scheme.py
tests/test_ibs_equilibrium.py
tests/test_ibs_growth_rates.py
tests/test_ibs_kicks.py
tests/test_iptocp_strongstrong.py
tests/test_lumi.py
tests/test_lumi_pic.py
tests/test_mean_std.py
tests/test_profiles.py
tests/test_slicer.py
tests/test_spacecharge.py
tests/test_temp_slicer.py
xfields/__init__.py
xfields/_version.py
xfields.egg-info/PKG-INFO
xfields.egg-info/SOURCES.txt
xfields.egg-info/dependency_links.txt
xfields.egg-info/entry_points.txt
xfields.egg-info/requires.txt
xfields.egg-info/top_level.txt
xfields/beam_elements/__init__.py
xfields/beam_elements/beambeam2d.py
xfields/beam_elements/beambeam3d.py
xfields/beam_elements/beambeam3dpic.py
xfields/beam_elements/electroncloud.py
xfields/beam_elements/electronlens_interpolated.py
xfields/beam_elements/element_with_slicer.py
xfields/beam_elements/spacecharge.py
xfields/beam_elements/temp_slicer.py
xfields/beam_elements/beambeam_src/beambeam.h
xfields/beam_elements/beambeam_src/beambeam2d.h
xfields/beam_elements/beambeam_src/beambeam3d.h
xfields/beam_elements/beambeam_src/beambeam3d_methods_for_strongstrong.h
xfields/beam_elements/beambeam_src/beambeam3d_ref_frame_changes.h
xfields/beam_elements/beambeam_src/beambeam3d_transport_sigmas.h
xfields/beam_elements/beambeam_src/beambeampic_methods.h
xfields/beam_elements/electroncloud_src/electroncloud.h
xfields/beam_elements/electronlens_src/electronlens_interpolated.h
xfields/beam_elements/spacecharge_src/spacecharge3d.h
xfields/beam_elements/spacecharge_src/spacechargebigaussian.h
