Metadata-Version: 2.4
Name: xfields
Version: 0.25.9
Summary: Field Maps and Particle In Cell
Author: G. Iadarola et al.
License-Expression: Apache-2.0
Project-URL: Homepage, https://xsuite.readthedocs.io/
Project-URL: Documentation, https://xsuite.readthedocs.io/
Project-URL: Source, https://github.com/xsuite/xfields
Project-URL: Bug Tracker, https://github.com/xsuite/xsuite/issues
Project-URL: Download, https://pypi.python.org/pypi/xfields
Requires-Python: >=3.10
License-File: LICENSE
Requires-Dist: numpy>=1.0
Requires-Dist: scipy
Requires-Dist: pandas
Requires-Dist: xobjects>=0.0.4
Requires-Dist: xtrack>=0.0.1
Provides-Extra: tests
Requires-Dist: pytest; extra == "tests"
Requires-Dist: h5py; extra == "tests"
Dynamic: license-file
